{
  "Snap": {
    "url": "https://snap.com",
    "founders": [],
    "ceo": null
  },
  "Snapdocs": {
    "url": "https://snapdocs.com",
    "founders": [],
    "ceo": null
  },
  "Snaplogic": {
    "url": "",
    "founders": [],
    "ceo": null
  },
  "Snapser": {
    "url": "",
    "founders": [],
    "ceo": null
  },
  "Snapsheet": {
    "url": "https://snapsheet.me",
    "founders": [],
    "ceo": null
  },
  "Snipp": {
    "url": "https://snipp.com",
    "founders": [],
    "ceo": null
  },
  "Snorkel AI": {
    "url": "https://snorkel.ai",
    "founders": [],
    "ceo": null
  },
  "Social Nation": {
    "url": "",
    "founders": [],
    "ceo": null
  },
  "Socialbakers": {
    "url": "",
    "founders": [],
    "ceo": null
  },
  "Socialcam": {
    "url": "",
    "founders": [],
    "ceo": null
  },
  "Socket": {
    "url": "",
    "founders": [],
    "ceo": null
  },
  "Socrata": {
    "url": "https://socrata.com",
    "founders": [],
    "ceo": null
  },
  "Socratic": {
    "url": "",
    "founders": [],
    "ceo": null
  },
  "Socure": {
    "url": "https://socure.com",
    "founders": [],
    "ceo": null
  },
  "Sofar Ocean": {
    "url": "https://sofarocean.com",
    "founders": [],
    "ceo": null
  },
  "Sofar Sounds Limited": {
    "url": "https://sofarsounds.com",
    "founders": [],
    "ceo": null
  },
  "Sof\u00eda": {
    "url": "",
    "founders": [],
    "ceo": null
  },
  "Soha Systems": {
    "url": "",
    "founders": [],
    "ceo": null
  },
  "Sola": {
    "url": "",
    "founders": [],
    "ceo": null
  },
  "Solace Health": {
    "url": "",
    "founders": [],
    "ceo": null
  },
  "Solana": {
    "url": "https://solana.com",
    "founders": [],
    "ceo": null
  },
  "SolarCity": {
    "url": "https://solarcity.com",
    "founders": [],
    "ceo": null
  },
  "SolarWinds": {
    "url": "https://solarwinds.com",
    "founders": [],
    "ceo": null
  },
  "Solid Power": {
    "url": "https://solidpowerbattery.com",
    "founders": [],
    "ceo": null
  },
  "SoloLearn": {
    "url": "https://sololearn.com",
    "founders": [],
    "ceo": null
  },
  "Solu Therapeutics": {
    "url": "https://solutherapeutics.com",
    "founders": [],
    "ceo": null
  },
  "Solugen": {
    "url": "https://solugen.com",
    "founders": [],
    "ceo": null
  },
  "SolveBio": {
    "url": "",
    "founders": [],
    "ceo": null
  },
  "Solvo": {
    "url": "",
    "founders": [],
    "ceo": null
  },
  "Somnee": {
    "url": "https://somneesleep.com",
    "founders": [],
    "ceo": null
  },
  "Sonder": {
    "url": "https://sonder.com",
    "founders": [],
    "ceo": null
  },
  "SonderMind": {
    "url": "https://sondermind.com",
    "founders": [],
    "ceo": null
  },
  "Sophos": {
    "url": "https://sophos.com",
    "founders": [],
    "ceo": null
  },
  "Sorare": {
    "url": "https://sorare.com",
    "founders": [],
    "ceo": null
  },
  "Sound.xyz": {
    "url": "",
    "founders": [],
    "ceo": null
  },
  "SoundCloud": {
    "url": "https://soundcloud.com",
    "founders": [],
    "ceo": null
  },
  "Sounding Board": {
    "url": "https://soundingboardinc.com",
    "founders": [],
    "ceo": null
  },
  "Sourceful": {
    "url": "",
    "founders": [],
    "ceo": null
  },
  "Sourcegraph": {
    "url": "https://sourcegraph.com",
    "founders": [],
    "ceo": null
  },
  "Sourcery Technologies": {
    "url": "",
    "founders": [],
    "ceo": null
  },
  "Sovos": {
    "url": "https://sovos.com",
    "founders": [],
    "ceo": null
  },
  "Sovrun": {
    "url": "",
    "founders": [],
    "ceo": null
  },
  "Soylent": {
    "url": "",
    "founders": [],
    "ceo": null
  },
  "Spade": {
    "url": "https://trispade.com",
    "founders": [],
    "ceo": null
  },
  "Sparkmeter": {
    "url": "https://sparkmeter.io",
    "founders": [],
    "ceo": null
  },
  "Speechify": {
    "url": "https://speechify.com",
    "founders": [],
    "ceo": null
  },
  "Spell": {
    "url": "https://spell.ml",
    "founders": [],
    "ceo": null
  },
  "Spellbook": {
    "url": "https://spellbook.legal",
    "founders": [],
    "ceo": null
  },
  "Spendesk": {
    "url": "",
    "founders": [],
    "ceo": null
  },
  "Sphere": {
    "url": "",
    "founders": [],
    "ceo": null
  }
}