{
  "InsightSquared": {
    "url": "https://insightsquared.com",
    "founders": [],
    "ceo": null
  },
  "Insightera": {
    "url": "",
    "founders": [],
    "ceo": null
  },
  "Insightly": {
    "url": "",
    "founders": [],
    "ceo": null
  },
  "Inspire Medical": {
    "url": "https://inspiresleep.com",
    "founders": [],
    "ceo": null
  },
  "Inspiren": {
    "url": "https://inspiren.com",
    "founders": [],
    "ceo": null
  },
  "Instabase": {
    "url": "https://instabase.com",
    "founders": [],
    "ceo": null
  },
  "Instart Logic": {
    "url": "",
    "founders": [],
    "ceo": null
  },
  "Instawork": {
    "url": "https://instawork.com",
    "founders": [],
    "ceo": null
  },
  "Instrumental": {
    "url": "https://instrumental.com",
    "founders": [],
    "ceo": null
  },
  "Integral Ad Science": {
    "url": "https://integralads.com",
    "founders": [],
    "ceo": null
  },
  "Intenseye": {
    "url": "",
    "founders": [],
    "ceo": null
  },
  "InterMune": {
    "url": "",
    "founders": [],
    "ceo": null
  },
  "Interana": {
    "url": "",
    "founders": [],
    "ceo": null
  },
  "Intrinsic": {
    "url": "",
    "founders": [],
    "ceo": null
  },
  "Intro": {
    "url": "",
    "founders": [],
    "ceo": null
  },
  "Introhive": {
    "url": "https://introhive.com",
    "founders": [],
    "ceo": null
  },
  "Intuit": {
    "url": "https://intuit.com",
    "founders": [],
    "ceo": null
  },
  "Invaio Sciences": {
    "url": "https://invaio.com",
    "founders": [],
    "ceo": null
  },
  "Inventa": {
    "url": "https://inventa.shop",
    "founders": [],
    "ceo": null
  },
  "Inversion Space": {
    "url": "https://inversionspace.com",
    "founders": [],
    "ceo": null
  },
  "Invoca": {
    "url": "https://invoca.com",
    "founders": [],
    "ceo": null
  },
  "Invoice2go": {
    "url": "https://invoice2go.com",
    "founders": [],
    "ceo": null
  },
  "Inworld AI": {
    "url": "https://inworld.ai",
    "founders": [],
    "ceo": null
  },
  "IonQ": {
    "url": "https://ionq.com",
    "founders": [],
    "ceo": null
  },
  "Ipsy": {
    "url": "https://ipsy.com",
    "founders": [],
    "ceo": null
  },
  "Iron Fish": {
    "url": "",
    "founders": [],
    "ceo": null
  },
  "Iron Ox": {
    "url": "https://ironox.com",
    "founders": [],
    "ceo": null
  },
  "IronNet": {
    "url": "https://ironnet.com",
    "founders": [],
    "ceo": null
  },
  "IronNet Cybersecurity": {
    "url": "https://ironnet.com",
    "founders": [],
    "ceo": null
  },
  "IronSpread": {
    "url": "",
    "founders": [],
    "ceo": null
  },
  "Ironclad": {
    "url": "https://ironcladapp.com",
    "founders": [],
    "ceo": null
  },
  "Irreverent Labs": {
    "url": "",
    "founders": [],
    "ceo": null
  },
  "Isomorphic Labs": {
    "url": "https://isomorphiclabs.com",
    "founders": [],
    "ceo": null
  },
  "Isovalent": {
    "url": "",
    "founders": [],
    "ceo": null
  },
  "Istra Research, Ltd.": {
    "url": "",
    "founders": [],
    "ceo": null
  },
  "ItsOn": {
    "url": "",
    "founders": [],
    "ceo": null
  },
  "JAMF": {
    "url": "https://jamf.com",
    "founders": [],
    "ceo": null
  },
  "JAMF Holdings Inc": {
    "url": "https://jamf.com",
    "founders": [],
    "ceo": null
  },
  "JD.com": {
    "url": "https://jd.com",
    "founders": [],
    "ceo": null
  },
  "JFrog": {
    "url": "https://jfrog.com",
    "founders": [],
    "ceo": null
  },
  "JFrog Ltd.": {
    "url": "https://jfrog.com",
    "founders": [],
    "ceo": null
  },
  "JOOR": {
    "url": "https://joor.com",
    "founders": [],
    "ceo": null
  },
  "Jask Labs, Inc.": {
    "url": "",
    "founders": [],
    "ceo": null
  },
  "Jasper": {
    "url": "https://jasper.ai",
    "founders": [],
    "ceo": null
  },
  "Jasper AI": {
    "url": "https://jasper.ai",
    "founders": [],
    "ceo": null
  },
  "Jeeves": {
    "url": "https://tryjeeves.com",
    "founders": [],
    "ceo": null
  },
  "Jerpix": {
    "url": "",
    "founders": [],
    "ceo": null
  },
  "Jet": {
    "url": "https://jet.com",
    "founders": [],
    "ceo": null
  },
  "Jet.com": {
    "url": "https://jet.com",
    "founders": [],
    "ceo": null
  },
  "Jiko": {
    "url": "https://jiko.io",
    "founders": [],
    "ceo": null
  }
}