{
  "Verdant Robotics": {
    "url": "https://verdantrobotics.com",
    "founders": [
      {"name": "Gabe Sibley", "linkedin": "https://www.linkedin.com/in/gabe-sibley/"},
      {"name": "Curtis Garner", "linkedin": "https://www.linkedin.com/in/curtisgarner/"},
      {"name": "Lawrence Ibarria", "linkedin": ""}
    ],
    "ceo": {"name": "Gabe Sibley", "linkedin": "https://www.linkedin.com/in/gabe-sibley/"}
  },
  "Verdigris Technologies": {
    "url": "https://verdigris.co",
    "founders": [
      {"name": "Mark Chung", "linkedin": "https://www.linkedin.com/in/markchung/"},
      {"name": "Thomas Chung", "linkedin": ""},
      {"name": "Jonathan Chu", "linkedin": ""}
    ],
    "ceo": {"name": "Mark Chung", "linkedin": "https://www.linkedin.com/in/markchung/"}
  },
  "Verdox": {
    "url": "https://verdox.com",
    "founders": [
      {"name": "Brian Baynes", "linkedin": "https://www.linkedin.com/in/brian-baynes-73a84/"},
      {"name": "T. Alan Hatton", "linkedin": ""},
      {"name": "Sahag Voskian", "linkedin": ""}
    ],
    "ceo": {"name": "Brian Baynes", "linkedin": "https://www.linkedin.com/in/brian-baynes-73a84/"}
  },
  "Vericel": {
    "url": "https://vericel.com",
    "founders": [],
    "ceo": {"name": "Nick Colangelo", "linkedin": "https://www.linkedin.com/in/nick-colangelo-578603338/"}
  },
  "Veriff": {
    "url": "https://veriff.com",
    "founders": [
      {"name": "Kaarel Kotkas", "linkedin": "https://ee.linkedin.com/in/kaarelkotkas"},
      {"name": "Janer Gorohhov", "linkedin": ""}
    ],
    "ceo": {"name": "Kaarel Kotkas", "linkedin": "https://ee.linkedin.com/in/kaarelkotkas"}
  },
  "Veriforce": {
    "url": "https://veriforce.com",
    "founders": [],
    "ceo": {"name": "Colby Lane", "linkedin": "https://www.linkedin.com/in/colby-lane-213a1645/"}
  },
  "Verint Systems": {
    "url": "https://verint.com",
    "founders": [
      {"name": "Dan Bodner", "linkedin": "https://www.linkedin.com/in/dan-bodner-verint/"}
    ],
    "ceo": {"name": "Dan Bodner", "linkedin": "https://www.linkedin.com/in/dan-bodner-verint/"}
  },
  "Veritone": {
    "url": "https://veritone.com",
    "founders": [
      {"name": "Ryan Steelberg", "linkedin": "https://www.linkedin.com/in/ryansteelberg"},
      {"name": "Chad Steelberg", "linkedin": ""}
    ],
    "ceo": {"name": "Ryan Steelberg", "linkedin": "https://www.linkedin.com/in/ryansteelberg"}
  },
  "Verizon Media": {
    "url": "",
    "founders": [],
    "ceo": {"name": "Guru Gowrappan", "linkedin": ""}
  },
  "Verkada": {
    "url": "https://verkada.com",
    "founders": [
      {"name": "Filip Kaliszan", "linkedin": "https://www.linkedin.com/in/kaliszan/"},
      {"name": "James Ren", "linkedin": ""},
      {"name": "Benjamin Bercovitz", "linkedin": "https://www.linkedin.com/in/benjaminbercovitz/"}
    ],
    "ceo": {"name": "Filip Kaliszan", "linkedin": "https://www.linkedin.com/in/kaliszan/"}
  },
  "Very Good Security": {
    "url": "https://vgs.io",
    "founders": [
      {"name": "Mahmoud Abdelkader", "linkedin": ""},
      {"name": "Marshall Jones", "linkedin": "https://www.linkedin.com/in/marshalljones2/"}
    ],
    "ceo": {"name": "Mahmoud Abdelkader", "linkedin": ""}
  },
  "Vesalius Therapeutics": {
    "url": "https://vesaliustx.com",
    "founders": [
      {"name": "Christopher P Austin", "linkedin": ""},
      {"name": "Douglas Cole", "linkedin": ""}
    ],
    "ceo": {"name": "Yasir Al-Wakeel", "linkedin": "https://www.linkedin.com/in/yasir-al-wakeel-0720a537/"}
  },
  "Vesta": {
    "url": "",
    "founders": [],
    "ceo": null
  },
  "Vetcor": {
    "url": "",
    "founders": [],
    "ceo": null
  },
  "Vetted": {
    "url": "",
    "founders": [],
    "ceo": null
  },
  "Veza": {
    "url": "https://veza.com",
    "founders": [
      {"name": "Tarun Thakur", "linkedin": "https://www.linkedin.com/in/tarunthakur/"}
    ],
    "ceo": {"name": "Tarun Thakur", "linkedin": "https://www.linkedin.com/in/tarunthakur/"}
  },
  "Viacycle": {
    "url": "",
    "founders": [],
    "ceo": null
  },
  "Viam": {
    "url": "https://viam.com",
    "founders": [
      {"name": "Eliot Horowitz", "linkedin": "https://www.linkedin.com/in/eliothorowitz"}
    ],
    "ceo": {"name": "Eliot Horowitz", "linkedin": "https://www.linkedin.com/in/eliothorowitz"}
  },
  "Viam Inc.": {
    "url": "https://viam.com",
    "founders": [
      {"name": "Eliot Horowitz", "linkedin": "https://www.linkedin.com/in/eliothorowitz"}
    ],
    "ceo": {"name": "Eliot Horowitz", "linkedin": "https://www.linkedin.com/in/eliothorowitz"}
  },
  "Vicarious": {
    "url": "https://vicarious.com",
    "founders": [
      {"name": "Scott Phoenix", "linkedin": "https://www.linkedin.com/in/dscottphoenix/"},
      {"name": "Dileep George", "linkedin": ""}
    ],
    "ceo": {"name": "Scott Phoenix", "linkedin": "https://www.linkedin.com/in/dscottphoenix/"}
  },
  "Vicarious Surgical": {
    "url": "https://vicarioussurgical.com",
    "founders": [
      {"name": "Adam Sachs", "linkedin": "https://www.linkedin.com/in/adamdsachs/"},
      {"name": "Sammy Khalifa", "linkedin": ""},
      {"name": "Barry Greene", "linkedin": ""}
    ],
    "ceo": {"name": "Stephen From", "linkedin": "https://www.linkedin.com/in/stephen-from-41ba53b/"}
  },
  "Vicinitas Therapeutics": {
    "url": "",
    "founders": [],
    "ceo": null
  },
  "Vida Health": {
    "url": "https://vida.com",
    "founders": [
      {"name": "Stephanie Tilenius", "linkedin": "https://www.linkedin.com/in/stephanie-tilenius-261b92132/"}
    ],
    "ceo": {"name": "Stephanie Tilenius", "linkedin": "https://www.linkedin.com/in/stephanie-tilenius-261b92132/"}
  },
  "Viki": {
    "url": "https://viki.com",
    "founders": [
      {"name": "Razmig Hovaghimian", "linkedin": ""},
      {"name": "Changseong Ho", "linkedin": ""},
      {"name": "Jiwon Moon", "linkedin": ""}
    ],
    "ceo": {"name": "Razmig Hovaghimian", "linkedin": ""}
  },
  "Villa": {
    "url": "https://villahomes.com",
    "founders": [
      {"name": "James Connolly", "linkedin": "https://www.linkedin.com/in/james-connolly-a19b0b64/"},
      {"name": "Sean Roberts", "linkedin": "https://www.linkedin.com/in/sean-roberts-49929218/"}
    ],
    "ceo": {"name": "Sean Roberts", "linkedin": "https://www.linkedin.com/in/sean-roberts-49929218/"}
  },
  "Vimeo": {
    "url": "https://vimeo.com",
    "founders": [
      {"name": "Jake Lodwick", "linkedin": ""},
      {"name": "Zach Klein", "linkedin": ""}
    ],
    "ceo": {"name": "Philip Moyer", "linkedin": "https://www.linkedin.com/in/phmoyer/"}
  },
  "Vinci4D": {
    "url": "https://vinci4d.com",
    "founders": [
      {"name": "Hardik Kabaria", "linkedin": "https://www.linkedin.com/in/hardikkabaria/"}
    ],
    "ceo": {"name": "Hardik Kabaria", "linkedin": "https://www.linkedin.com/in/hardikkabaria/"}
  },
  "Vine": {
    "url": "https://vine.co",
    "founders": [],
    "ceo": null
  },
  "Vinted": {
    "url": "https://vinted.com",
    "founders": [
      {"name": "Milda Mitkute", "linkedin": ""},
      {"name": "Justas Janauskas", "linkedin": "https://lt.linkedin.com/in/jjanauskas"}
    ],
    "ceo": {"name": "Thomas Plantenga", "linkedin": ""}
  },
  "Vinyl Equity": {
    "url": "",
    "founders": [
      {"name": "Rob Schoder Jr", "linkedin": ""},
      {"name": "Poornaprajna Udupi", "linkedin": ""}
    ],
    "ceo": {"name": "Rob Schoder Jr", "linkedin": ""}
  },
  "Virool": {
    "url": "",
    "founders": [
      {"name": "Alexander Debelov", "linkedin": "https://www.linkedin.com/in/alexander-debelov-aa97b62b8/"}
    ],
    "ceo": {"name": "Alexander Debelov", "linkedin": "https://www.linkedin.com/in/alexander-debelov-aa97b62b8/"}
  },
  "Virta Health": {
    "url": "https://virtahealth.com",
    "founders": [
      {"name": "Sami Inkinen", "linkedin": "https://www.linkedin.com/in/samiinkinen"}
    ],
    "ceo": {"name": "Sami Inkinen", "linkedin": "https://www.linkedin.com/in/samiinkinen"}
  },
  "Virtual Marine Technology": {
    "url": "https://virtualmarine.ca",
    "founders": [],
    "ceo": null
  },
  "Virtually Human Studio": {
    "url": "",
    "founders": [],
    "ceo": null
  },
  "Virtusa": {
    "url": "https://virtusa.com",
    "founders": [
      {"name": "Kris Canekeratne", "linkedin": "https://www.linkedin.com/in/kris-canekeratne/"},
      {"name": "Sandy Gillis", "linkedin": ""},
      {"name": "John Gillis", "linkedin": ""},
      {"name": "Tushara Canekeratne", "linkedin": ""}
    ],
    "ceo": {"name": "Nitesh Banga", "linkedin": "https://www.linkedin.com/in/nitesh-banga-710248b/"}
  },
  "Visan": {
    "url": "",
    "founders": [],
    "ceo": null
  },
  "Vise": {
    "url": "https://vise.com",
    "founders": [
      {"name": "Samir Vasavada", "linkedin": "https://www.linkedin.com/in/samir-vasavada-160865ab/"},
      {"name": "Runik Mehrotra", "linkedin": "https://www.linkedin.com/in/runik-mehrotra/"}
    ],
    "ceo": {"name": "Samir Vasavada", "linkedin": "https://www.linkedin.com/in/samir-vasavada-160865ab/"}
  },
  "Visible Sensors": {
    "url": "https://visiblesensors.com",
    "founders": [],
    "ceo": null
  },
  "Visolis": {
    "url": "",
    "founders": [],
    "ceo": null
  },
  "Visual.ly": {
    "url": "https://visual.ly",
    "founders": [
      {"name": "Stew Langille", "linkedin": ""},
      {"name": "Lee Sherman", "linkedin": ""},
      {"name": "Tal Siach", "linkedin": ""},
      {"name": "Adam Breckler", "linkedin": ""}
    ],
    "ceo": {"name": "Matt Cooper", "linkedin": ""}
  },
  "Vitally": {
    "url": "https://vitally.io",
    "founders": [
      {"name": "Jamie Davidson", "linkedin": "https://www.linkedin.com/in/davidsonjamie/"},
      {"name": "Patrick Vatterott", "linkedin": ""}
    ],
    "ceo": {"name": "Jamie Davidson", "linkedin": "https://www.linkedin.com/in/davidsonjamie/"}
  },
  "Vium": {
    "url": "https://vium.com",
    "founders": [],
    "ceo": {"name": "Laura Schaevitz", "linkedin": ""}
  },
  "Viz.ai": {
    "url": "https://viz.ai",
    "founders": [
      {"name": "Chris Mansi", "linkedin": "https://www.linkedin.com/in/chrismansimd/"},
      {"name": "David Golan", "linkedin": ""}
    ],
    "ceo": {"name": "Chris Mansi", "linkedin": "https://www.linkedin.com/in/chrismansimd/"}
  },
  "Vizcom": {
    "url": "",
    "founders": [],
    "ceo": null
  },
  "Vlocity": {
    "url": "https://vlocity.com",
    "founders": [
      {"name": "James Ramsey", "linkedin": ""},
      {"name": "Mark Armenante", "linkedin": ""},
      {"name": "Craig Ramsey", "linkedin": "https://www.linkedin.com/in/craig-ramsey-7077aa7/"},
      {"name": "David Schmaier", "linkedin": "https://www.linkedin.com/in/david-schmaier-70476b43/"},
      {"name": "Jeff Amann", "linkedin": ""},
      {"name": "Young Sohn", "linkedin": ""}
    ],
    "ceo": {"name": "David Schmaier", "linkedin": "https://www.linkedin.com/in/david-schmaier-70476b43/"}
  },
  "Voidpet": {
    "url": "",
    "founders": [],
    "ceo": null
  },
  "Voldex": {
    "url": "",
    "founders": [],
    "ceo": null
  },
  "Volteras": {
    "url": "https://volteras.com",
    "founders": [
      {"name": "Peter Wilson", "linkedin": "https://www.linkedin.com/in/peter-wilson-1412a5126/"}
    ],
    "ceo": {"name": "Peter Wilson", "linkedin": "https://www.linkedin.com/in/peter-wilson-1412a5126/"}
  },
  "Voltron Data": {
    "url": "https://voltrondata.com",
    "founders": [
      {"name": "Josh Patterson", "linkedin": ""},
      {"name": "Wes McKinney", "linkedin": ""},
      {"name": "Rodrigo Aramburú", "linkedin": ""},
      {"name": "Darren Haas", "linkedin": ""}
    ],
    "ceo": {"name": "Josh Patterson", "linkedin": ""}
  },
  "Volue": {
    "url": "https://volue.com",
    "founders": [],
    "ceo": {"name": "Trond Straume", "linkedin": "https://no.linkedin.com/in/trondstraume"}
  }
}
