{
  "Massive Health": {
    "url": "",
    "founders": [],
    "ceo": null
  },
  "MasterClass": {
    "url": "https://masterclass.com",
    "founders": [],
    "ceo": null
  },
  "MatX": {
    "url": "https://matx.com",
    "founders": [],
    "ceo": null
  },
  "Match.com": {
    "url": "https://match.com",
    "founders": [],
    "ceo": null
  },
  "Matchday": {
    "url": "",
    "founders": [],
    "ceo": null
  },
  "Matera": {
    "url": "",
    "founders": [],
    "ceo": null
  },
  "Material Bank": {
    "url": "https://materialbank.com",
    "founders": [],
    "ceo": null
  },
  "Material Security": {
    "url": "",
    "founders": [],
    "ceo": null
  },
  "Mati Carbon": {
    "url": "https://maticarbontech.com",
    "founders": [],
    "ceo": null
  },
  "Matik": {
    "url": "",
    "founders": [],
    "ceo": null
  },
  "Matillion": {
    "url": "https://matillion.com",
    "founders": [],
    "ceo": null
  },
  "Matillion Limited": {
    "url": "https://matillion.com",
    "founders": [],
    "ceo": null
  },
  "Matter Labs": {
    "url": "https://matter-labs.io",
    "founders": [],
    "ceo": null
  },
  "MatterPort": {
    "url": "https://matterport.com",
    "founders": [],
    "ceo": null
  },
  "Mattermark": {
    "url": "https://mattermark.com",
    "founders": [],
    "ceo": null
  },
  "Mattermost, Inc.": {
    "url": "https://mattermost.com",
    "founders": [],
    "ceo": null
  },
  "Matternet": {
    "url": "",
    "founders": [],
    "ceo": null
  },
  "Matterport": {
    "url": "https://matterport.com",
    "founders": [],
    "ceo": null
  },
  "Maven": {
    "url": "https://maven.com",
    "founders": [],
    "ceo": null
  },
  "Mavrx": {
    "url": "https://mavrx.com",
    "founders": [],
    "ceo": null
  },
  "Maxio": {
    "url": "https://maxio.com",
    "founders": [],
    "ceo": null
  },
  "Maybern": {
    "url": "https://maybern.com",
    "founders": [],
    "ceo": null
  },
  "Mayvenn": {
    "url": "https://mayvenn.com",
    "founders": [],
    "ceo": null
  },
  "Maza": {
    "url": "",
    "founders": [],
    "ceo": null
  },
  "Maze": {
    "url": "https://maze.co",
    "founders": [],
    "ceo": null
  },
  "Maze Therapeutics": {
    "url": "https://mazetherapeutics.com",
    "founders": [],
    "ceo": null
  },
  "McAfee": {
    "url": "https://mcafee.com",
    "founders": [],
    "ceo": null
  },
  "MealPal": {
    "url": "https://mealpal.com",
    "founders": [],
    "ceo": null
  },
  "MedStack": {
    "url": "https://medstack.co",
    "founders": [],
    "ceo": null
  },
  "Medable": {
    "url": "https://medable.com",
    "founders": [],
    "ceo": null
  },
  "Media Chain": {
    "url": "",
    "founders": [],
    "ceo": null
  },
  "MediaSpike": {
    "url": "",
    "founders": [],
    "ceo": null
  },
  "Medical Informatics": {
    "url": "https://medicalinformatics.com",
    "founders": [],
    "ceo": null
  },
  "MedicureInc": {
    "url": "https://medicure.com",
    "founders": [],
    "ceo": null
  },
  "Medigram": {
    "url": "",
    "founders": [],
    "ceo": null
  },
  "Medium": {
    "url": "https://medium.com",
    "founders": [],
    "ceo": null
  },
  "Medley": {
    "url": "",
    "founders": [],
    "ceo": null
  },
  "Medmonk": {
    "url": "",
    "founders": [],
    "ceo": null
  },
  "Meesho": {
    "url": "https://meesho.com",
    "founders": [],
    "ceo": null
  },
  "MeetMe": {
    "url": "",
    "founders": [],
    "ceo": null
  },
  "Meetup": {
    "url": "https://meetup.com",
    "founders": [],
    "ceo": null
  },
  "Meituan": {
    "url": "https://meituan.com",
    "founders": [],
    "ceo": null
  },
  "Mejuri": {
    "url": "https://mejuri.com",
    "founders": [],
    "ceo": null
  },
  "Mem": {
    "url": "",
    "founders": [],
    "ceo": null
  },
  "Mem Protocol": {
    "url": "",
    "founders": [],
    "ceo": null
  },
  "Memora": {
    "url": "",
    "founders": [],
    "ceo": null
  },
  "Meraki": {
    "url": "https://meraki.cisco.com",
    "founders": [],
    "ceo": null
  },
  "Mercado Libre": {
    "url": "https://mercadolibre.com",
    "founders": [],
    "ceo": null
  },
  "Mercantile": {
    "url": "",
    "founders": [],
    "ceo": null
  },
  "Mercor": {
    "url": "https://mercor.com",
    "founders": [],
    "ceo": null
  }
}